{
  "symbol": "NVDA",
  "from_date": "2021-03-01",
  "to_date": "2021-03-31",
  "total_news_fetched": 177,
  "filtered_out": 89,
  "valid_news": 88,
  "processed_count": 88,
  "generated_time": "2025-06-03 01:16:37",
  "news_data": [
    {
      "headline": "These Options Traders Think Nvidia Stock Is Going Higher",
      "source": "benzinga",
      "datetime": 1617235200,
      "publish_date": "2021-04-01 00:00:00",
      "original_url": "https://finnhub.io/api/news?id=238cfb879228d808b71ca2bb0fc3e7fa2715d2dcee73f693efdd7eb5ec3deb07",
      "final_url": "https://www.benzinga.com/markets/options/21/04/20449342/these-options-traders-think-nvidia-stock-is-going-higher",
      "is_yahoo_finance": false,
      "has_continue_reading": false,
      "url_check_status": "success",
      "url_check_error": null
    },
    {
      "headline": "World-leading AI research and inclusion at the forefront of this year’s NVIDIA GTC",
      "source": "https://venturebeat.com",
      "datetime": 1617196237,
      "publish_date": "2021-03-31 13:10:37",
      "original_url": "https://finnhub.io/api/news?id=2f9829f9dbace93406a008f8d5cc27107310bf6515ed1e4b7c9e93d80312510d",
      "final_url": "https://venturebeat.com/ai/world-leading-ai-research-and-inclusion-at-the-forefront-of-this-years-nvidia-gtc/",
      "is_yahoo_finance": false,
      "has_continue_reading": false,
      "url_check_status": "success",
      "url_check_error": null
    },
    {
      "headline": "Nvidia gives all RTX 30 GPU resizable BAR support",
      "source": "https://www.windowscentral.com",
      "datetime": 1617132543,
      "publish_date": "2021-03-30 19:29:03",
      "original_url": "https://finnhub.io/api/news?id=ecbbc95d93dbd44b60f1874c3bb84abc0bf9723bd0bc396c6f95a9d4ff745153",
      "final_url": "https://www.windowscentral.com/all-nvidia-rtx-30-series-desktop-gpus-now-have-resizable-bar-support",
      "is_yahoo_finance": false,
      "has_continue_reading": false,
      "url_check_status": "success",
      "url_check_error": null
    },
    {
      "headline": "Nvidia’s Resizable BAR frame rate boosts now available on all 30-series GPUs",
      "source": "https://www.theverge.com",
      "datetime": 1617111834,
      "publish_date": "2021-03-30 13:43:54",
      "original_url": "https://finnhub.io/api/news?id=79881bbb4a6f16e2fe1355295e750ed51ae52d3736bb84d13fb1f25b29baa084",
      "final_url": "https://www.theverge.com/2021/3/30/22357980/nvidia-resizable-bar-support-30-series-gpus-available-now",
      "is_yahoo_finance": false,
      "has_continue_reading": false,
      "url_check_status": "success",
      "url_check_error": null
    },
    {
      "headline": "Volvo Collaborates With Aurora For Autonomous Truck Development",
      "source": "Benzinga",
      "datetime": 1617109500,
      "publish_date": "2021-03-30 13:05:00",
      "original_url": "https://finnhub.io/api/news?id=41ef913a9637027df38c8cd752560ddcc91f5c231b7a8e50c655b1160d893f31",
      "final_url": "https://www.benzinga.com/news/21/03/20407210/volvo-collaborates-with-aurora-for-autonomous-truck-development",
      "is_yahoo_finance": false,
      "has_continue_reading": false,
      "url_check_status": "success",
      "url_check_error": null
    },
    {
      "headline": "Artificial Intelligence Stocks: Best Stocks To Buy and Watch Now",
      "source": "https://www.gobankingrates.com",
      "datetime": 1617052503,
      "publish_date": "2021-03-29 21:15:03",
      "original_url": "https://finnhub.io/api/news?id=2b644f056cce7b5e630e3bec30aabd573fd3a35748406685f29dc3d34bd8d16f",
      "final_url": "https://www.gobankingrates.com/investing/stocks/artificial-intelligence-stocks/",
      "is_yahoo_finance": false,
      "has_continue_reading": false,
      "url_check_status": "success",
      "url_check_error": null
    },
    {
      "headline": "The First 39 Companies In Cathie Wood's Ark Invest Space ETF",
      "source": "Benzinga",
      "datetime": 1617036600,
      "publish_date": "2021-03-29 16:50:00",
      "original_url": "https://finnhub.io/api/news?id=6935019e4350e4df732112f51c4682a1a45802dfa8747c176316728b775a55a3",
      "final_url": "https://www.benzinga.com/news/21/03/20388717/the-first-39-companies-in-cathie-woods-ark-invest-space-etf",
      "is_yahoo_finance": false,
      "has_continue_reading": false,
      "url_check_status": "success",
      "url_check_error": null
    },
    {
      "headline": "NVIDIA Launches Broadcast App For Streamers. How Does It Work?",
      "source": "https://analyticsindiamag.com",
      "datetime": 1616841000,
      "publish_date": "2021-03-27 10:30:00",
      "original_url": "https://finnhub.io/api/news?id=d3e870eaba5a2756ddc77cef42a66505040b4eae77ce6167d9fb2e5e093cf1b8",
      "final_url": "https://analyticsindiamag.com/global-tech/nvidia-launches-broadcast-app-for-streamers-how-does-it-work/",
      "is_yahoo_finance": false,
      "has_continue_reading": false,
      "url_check_status": "success",
      "url_check_error": null
    },
    {
      "headline": "A perfect storm: Why graphics cards cost so much now",
      "source": "https://www.pcworld.com",
      "datetime": 1616630400,
      "publish_date": "2021-03-25 00:00:00",
      "original_url": "https://finnhub.io/api/news?id=981e0f2418d10922d8fc5aeee9144a5d265e2a67600cf135ef423d152e6890f4",
      "final_url": "https://www.pcworld.com/article/394292/a-perfect-storm-why-graphics-cards-cost-so-much-now.html",
      "is_yahoo_finance": false,
      "has_continue_reading": false,
      "url_check_status": "success",
      "url_check_error": null
    },
    {
      "headline": "Nvidia GeForce Now Game Streaming Service Updates Tiers",
      "source": "https://www.forbes.com",
      "datetime": 1616630400,
      "publish_date": "2021-03-25 00:00:00",
      "original_url": "https://finnhub.io/api/news?id=cdd9640ac44041f3b9f93835ecfeccd97b8d4820d7b81f82323bc1688dd4f6c8",
      "final_url": "https://www.forbes.com/sites/tiriasresearch/2021/03/25/nvidia-geforce-now-game-streaming-service-updates-tiers/",
      "is_yahoo_finance": false,
      "has_continue_reading": false,
      "url_check_status": "success",
      "url_check_error": null
    },
    {
      "headline": "Why is Nvidia a better investment than Intel in a virus-hit market? | AlphaStreet",
      "source": "https://news.alphastreet.com",
      "datetime": 1616588647,
      "publish_date": "2021-03-24 12:24:07",
      "original_url": "https://finnhub.io/api/news?id=cb2519c32e60e02b7d2b87acaeeb34636f6d827c6e39cbb2ba30a31a8b77e0e2",
      "final_url": "https://news.alphastreet.com/why-nvidia-is-a-better-investment-than-intel-in-virus-hit-market/",
      "is_yahoo_finance": false,
      "has_continue_reading": false,
      "url_check_status": "success",
      "url_check_error": null
    },
    {
      "headline": "Scalpers Now Move to Lower-End GPUs as Prices Doubled; PS5 Restock in Better Shape, Though",
      "source": "https://www.techtimes.com",
      "datetime": 1616551200,
      "publish_date": "2021-03-24 02:00:00",
      "original_url": "https://finnhub.io/api/news?id=0261cc51757efabd537c5f93a87911b8c315815fd0407f585fa67ad067edc1c4",
      "final_url": "https://www.techtimes.com/articles/258331/20210323/ps5-restock-scalpers-decreased-gpu-nvidia-gtx-1050-ti-price-ebay.htm",
      "is_yahoo_finance": false,
      "has_continue_reading": false,
      "url_check_status": "success",
      "url_check_error": null
    },
    {
      "headline": "Nintendo Switch Pro to Use DLSS to Unlock 4K Gaming | Digital Trends",
      "source": "https://www.digitaltrends.com",
      "datetime": 1616532025,
      "publish_date": "2021-03-23 20:40:25",
      "original_url": "https://finnhub.io/api/news?id=94080e27a83f163f36ddaa549f9345005c5889b5a5fff04d89ca8707fd569fbc",
      "final_url": "https://www.digitaltrends.com/computing/nintendo-switch-pro-dlss-nvidia-4k/",
      "is_yahoo_finance": false,
      "has_continue_reading": false,
      "url_check_status": "success",
      "url_check_error": null
    },
    {
      "headline": "Market Chatter: NVIDIA Chips to be Reportedly Used in New Nintendo Switch | MarketScreener",
      "source": "https://www.marketscreener.com",
      "datetime": 1616520901,
      "publish_date": "2021-03-23 17:35:01",
      "original_url": "https://finnhub.io/api/news?id=d320c1131fc47f36025c0640f73d3b0bd3710ed105d106a0015c0897ce753064",
      "final_url": "https://www.marketscreener.com/quote/stock/NVIDIA-CORPORATION-57355629/news/Market-Chatter-NVIDIA-Chips-to-be-Reportedly-Used-in-New-Nintendo-Switch-32766447/",
      "is_yahoo_finance": false,
      "has_continue_reading": false,
      "url_check_status": "success",
      "url_check_error": null
    },
    {
      "headline": "The street prices of Nvidia and AMD GPUs are utterly out of control",
      "source": "https://www.theverge.com",
      "datetime": 1616502600,
      "publish_date": "2021-03-23 12:30:00",
      "original_url": "https://finnhub.io/api/news?id=97e26fb9603e8bf9b533ab297e2961c446828b89465de6486fad1cc5ef9e590b",
      "final_url": "https://www.theverge.com/2021/3/23/22345891/nvidia-amd-rtx-gpus-price-scalpers-ebay-graphics-cards",
      "is_yahoo_finance": false,
      "has_continue_reading": false,
      "url_check_status": "success",
      "url_check_error": null
    },
    {
      "headline": "Nintendo Targets Upgraded Cost-Effective Nvidia Graphics Chip In 2021 Switch",
      "source": "Benzinga",
      "datetime": 1616488980,
      "publish_date": "2021-03-23 08:43:00",
      "original_url": "https://finnhub.io/api/news?id=ce91af1a2b25487a46b77c69bac5bcfa28a2e9cda116ddbf1eb6b28fd6f5d864",
      "final_url": "https://www.benzinga.com/news/21/03/20294671/nintendo-targets-upgraded-cost-effective-nvidia-graphics-chip-in-2021-switch",
      "is_yahoo_finance": false,
      "has_continue_reading": false,
      "url_check_status": "success",
      "url_check_error": null
    },
    {
      "headline": "NEXCOM Partners with NVIDIA to Develop Advanced Ethernet Solutions",
      "source": "https://www.einpresswire.com",
      "datetime": 1616485830,
      "publish_date": "2021-03-23 07:50:30",
      "original_url": "https://finnhub.io/api/news?id=6b375cba3ca7ca65fba59cfc44cef32e764e158eb859d0ef09a18ea920bb3db7",
      "final_url": "https://www.einpresswire.com/article/537353930/nexcom-partners-with-nvidia-to-develop-advanced-ethernet-solutions",
      "is_yahoo_finance": false,
      "has_continue_reading": false,
      "url_check_status": "success",
      "url_check_error": null
    },
    {
      "headline": "VMware And NVIDIA Bring A100 GPUs To vSphere 7 To Virtualize AI Acceleration",
      "source": "https://www.forbes.com",
      "datetime": 1616457600,
      "publish_date": "2021-03-23 00:00:00",
      "original_url": "https://finnhub.io/api/news?id=ab3c7aa98f8b95f17ea898d8d399659145d09616e6039fe300ad10b961994f8c",
      "final_url": "https://www.forbes.com/sites/janakirammsv/2021/03/23/vmware-and-nvidia-bring-a100-gpus-to-vsphere-7-to-virtualize-ai-acceleration/",
      "is_yahoo_finance": false,
      "has_continue_reading": false,
      "url_check_status": "success",
      "url_check_error": null
    },
    {
      "headline": "How NVIDIA And VMware Aim To Make Enterprise AI Easier With Joint Solutions",
      "source": "https://www.forbes.com",
      "datetime": 1616457600,
      "publish_date": "2021-03-23 00:00:00",
      "original_url": "https://finnhub.io/api/news?id=77bfb5d36d823f36cfb37867de5f8a20898c18364acb1f5e32ac1ee15b4555e8",
      "final_url": "https://www.forbes.com/sites/maribellopez/2021/03/23/how-nvidia-and-vmware-aim-to-make-enterprise-ai-easier-with-joint-solutions/",
      "is_yahoo_finance": false,
      "has_continue_reading": false,
      "url_check_status": "success",
      "url_check_error": null
    },
    {
      "headline": "Nvidia RTX 3080 Ti and 3070 Ti Coming Soon, But Not For You | Digital Trends",
      "source": "https://www.digitaltrends.com",
      "datetime": 1616441677,
      "publish_date": "2021-03-22 19:34:37",
      "original_url": "https://finnhub.io/api/news?id=4bc5d5b562c717f185eeaa51a9a78c93a9572a5a40e6495b1a45f4f44fa39636",
      "final_url": "https://www.digitaltrends.com/computing/",
      "is_yahoo_finance": false,
      "has_continue_reading": false,
      "url_check_status": "success",
      "url_check_error": null
    },
    {
      "headline": "The QQQ Rallied Today. Here's Why.",
      "source": "benzinga",
      "datetime": 1616371200,
      "publish_date": "2021-03-22 00:00:00",
      "original_url": "https://finnhub.io/api/news?id=be7da518305ab7b331a5a871489545e49be0fb4ecdc448dd0d9fc166663bd302",
      "final_url": "https://www.benzinga.com/news/21/03/20286063/the-qqq-rallied-today-heres-why",
      "is_yahoo_finance": false,
      "has_continue_reading": false,
      "url_check_status": "success",
      "url_check_error": null
    },
    {
      "headline": "10 Information Technology Stocks With Unusual Options Alerts In Today's Session",
      "source": "Benzinga",
      "datetime": 1616417220,
      "publish_date": "2021-03-22 12:47:00",
      "original_url": "https://finnhub.io/api/news?id=80ec4d3590e35c07bde6107845f878440beedff96a98175f856ad5b57f3f9333",
      "final_url": "https://www.benzinga.com/news/21/03/20282484/10-information-technology-stocks-with-unusual-options-alerts-in-todays-session",
      "is_yahoo_finance": false,
      "has_continue_reading": false,
      "url_check_status": "success",
      "url_check_error": null
    },
    {
      "headline": "COVID-19 Recovery May Be Driving New Commodity Supercycle",
      "source": "benzinga",
      "datetime": 1616371200,
      "publish_date": "2021-03-22 00:00:00",
      "original_url": "https://finnhub.io/api/news?id=b3d2f43ed390539ffef2c5f3471ed95687b293679955a9782a95edd8a0f89764",
      "final_url": "https://www.benzinga.com/news/21/03/20282635/covid-19-recovery-may-be-driving-new-commodity-supercycle",
      "is_yahoo_finance": false,
      "has_continue_reading": false,
      "url_check_status": "success",
      "url_check_error": null
    },
    {
      "headline": "These beaten-down tech stocks may be worth their high valuations, two traders say",
      "source": "CNBC",
      "datetime": 1616416039,
      "publish_date": "2021-03-22 12:27:19",
      "original_url": "https://finnhub.io/api/news?id=8a4846b1b6aa16addf3b6a8a0c84cec16a27ebd9e26238add0d5a45a4b67b62c",
      "final_url": "https://www.cnbc.com/2021/03/22/these-beaten-down-tech-stocks-may-be-worth-their-high-valuations.html",
      "is_yahoo_finance": false,
      "has_continue_reading": false,
      "url_check_status": "success",
      "url_check_error": null
    },
    {
      "headline": "Use The Current Weakness In Growth Stocks To Buy Long-Term Winners",
      "source": "https://www.forbes.com",
      "datetime": 1616112000,
      "publish_date": "2021-03-19 00:00:00",
      "original_url": "https://finnhub.io/api/news?id=4a83b40e8ba831e8b85787bfe1efb9e3cbb621e34b0d7599ad1f2c2533738520",
      "final_url": "https://www.forbes.com/sites/randywatts/2021/03/19/use-the-current-weakness-in-growth-stocks-to-buy-long-term-winners/",
      "is_yahoo_finance": false,
      "has_continue_reading": false,
      "url_check_status": "success",
      "url_check_error": null
    },
    {
      "headline": "NVIDIA GeForce Now membership changes, existing Founders stay the same",
      "source": "https://www.windowscentral.com",
      "datetime": 1616085906,
      "publish_date": "2021-03-18 16:45:06",
      "original_url": "https://finnhub.io/api/news?id=5f47463c0080cacb0e3d6b815b01f5f405cd5ac740ad8aaeeaa041959840caf9",
      "final_url": "https://www.windowscentral.com/nvidia-ends-geforce-now-founders-memberships-existing-members-keep-reduced-rate",
      "is_yahoo_finance": false,
      "has_continue_reading": false,
      "url_check_status": "success",
      "url_check_error": null
    },
    {
      "headline": "NVIDIA GeForce Now Announces Increase in Subscription Fee",
      "source": "https://www.techtimes.com",
      "datetime": 1616084900,
      "publish_date": "2021-03-18 16:28:20",
      "original_url": "https://finnhub.io/api/news?id=8231d2fd8ec8178b41f134e3fdba98e01a97e0c2f96f5e2bb5c93f3e5e77cb41",
      "final_url": "https://www.techtimes.com/articles/258161/20210318/nvidia-geforce-now-announces-increase-in-subscription-fee-gaming-service-costs-10-a-month.htm",
      "is_yahoo_finance": false,
      "has_continue_reading": false,
      "url_check_status": "success",
      "url_check_error": null
    },
    {
      "headline": "GeForce NOW Raises Prices, But Not for Founders - Thurrott.com",
      "source": "https://www.thurrott.com",
      "datetime": 1616082491,
      "publish_date": "2021-03-18 15:48:11",
      "original_url": "https://finnhub.io/api/news?id=a750964dafb641637e6aac19d9fa9afa0c7754aeecab23ae680a3d927dcd7f6d",
      "final_url": "https://www.thurrott.com/games/248263/geforce-now-raises-prices-but-not-for-founders",
      "is_yahoo_finance": false,
      "has_continue_reading": false,
      "url_check_status": "success",
      "url_check_error": null
    },
    {
      "headline": "GeForce Now’s new Priority plan offers Founders benefits but with an expensive downside",
      "source": "https://www.slashgear.com",
      "datetime": 1616082213,
      "publish_date": "2021-03-18 15:43:33",
      "original_url": "https://finnhub.io/api/news?id=49c495f101be9efc0d29f648a3d35955a6532a8380f3361007a944289b23b041",
      "final_url": "https://www.slashgear.com/geforce-nows-new-priority-plan-offers-founders-benefits-but-with-an-expensive-downside-18664395/",
      "is_yahoo_finance": false,
      "has_continue_reading": false,
      "url_check_status": "success",
      "url_check_error": null
    },
    {
      "headline": "Can’t buy an Nvidia RTX 3080 GPU? You could win one in this Microsoft Flight Simulator contest",
      "source": "https://www.techradar.com",
      "datetime": 1616079913,
      "publish_date": "2021-03-18 15:05:13",
      "original_url": "https://finnhub.io/api/news?id=dd224175a272f1964c5a9dcc36e4bf0401dccc597d54bb91d357cdba374828c6",
      "final_url": "https://www.techradar.com/news/cant-buy-an-nvidia-rtx-3080-gpu-you-could-win-one-in-this-microsoft-flight-simulator-contest",
      "is_yahoo_finance": false,
      "has_continue_reading": false,
      "url_check_status": "success",
      "url_check_error": null
    },
    {
      "headline": "Nvidia will double GeForce Now subscription price to $10 a month for new members",
      "source": "https://venturebeat.com",
      "datetime": 1616072418,
      "publish_date": "2021-03-18 13:00:18",
      "original_url": "https://finnhub.io/api/news?id=f7a51166cc37111abd4ca0cfcad55277d2ffdec0f2c40a092f2cb7d476a33717",
      "final_url": "https://venturebeat.com/games/nvidia-will-double-geforce-now-subscription-price-to-10-a-month-for-new-members/",
      "is_yahoo_finance": false,
      "has_continue_reading": false,
      "url_check_status": "success",
      "url_check_error": null
    },
    {
      "headline": "Nvidia is doubling the price of its GeForce Now cloud gaming service for new users",
      "source": "https://www.theverge.com",
      "datetime": 1616072400,
      "publish_date": "2021-03-18 13:00:00",
      "original_url": "https://finnhub.io/api/news?id=1fac13df40e1159f3e62e3adfa335d34cdf4362b227a2377612fd75e838dc428",
      "final_url": "https://www.theverge.com/2021/3/18/22336600/nvidia-geforce-now-price-tier-cloud-gaming-subscription",
      "is_yahoo_finance": false,
      "has_continue_reading": false,
      "url_check_status": "success",
      "url_check_error": null
    },
    {
      "headline": "GeForce Now 'Priority' tier doubles the price to $9.99/month - 9to5Google",
      "source": "https://9to5google.com",
      "datetime": 1616072400,
      "publish_date": "2021-03-18 13:00:00",
      "original_url": "https://finnhub.io/api/news?id=8a02ec4577f6e33ae7b2816eaae4591e9be9ae9bed104f5b3ef3b67099bc7cff",
      "final_url": "https://9to5google.com/2021/03/18/geforce-now-priority-tier-price/",
      "is_yahoo_finance": false,
      "has_continue_reading": false,
      "url_check_status": "success",
      "url_check_error": null
    },
    {
      "headline": "NVIDIA Enhances Quality, Introduces New Membership Tiers To Its GFN Game Streaming Service",
      "source": "https://www.forbes.com",
      "datetime": 1616025600,
      "publish_date": "2021-03-18 00:00:00",
      "original_url": "https://finnhub.io/api/news?id=12a03dd2571780b2fb08d195e64663824b7ca1cccb88685099f1eeb5d4093608",
      "final_url": "https://www.forbes.com/sites/marcochiappetta/2021/03/18/nvidia-enhances-quality-introduces-new-membership-tiers-to-its-gfn-game-streaming-service/",
      "is_yahoo_finance": false,
      "has_continue_reading": false,
      "url_check_status": "success",
      "url_check_error": null
    },
    {
      "headline": "Nvidia hypes up new games implementing DLSS with Unreal Engine plugin",
      "source": "https://venturebeat.com",
      "datetime": 1616013497,
      "publish_date": "2021-03-17 20:38:17",
      "original_url": "https://finnhub.io/api/news?id=ead464fa689ebb08394dee9dfaaab95f2864f4b6a6d09b586c5a2e327944175d",
      "final_url": "https://venturebeat.com/games/dlss-unreal-engine/",
      "is_yahoo_finance": false,
      "has_continue_reading": false,
      "url_check_status": "success",
      "url_check_error": null
    },
    {
      "headline": "SPECTRUM PR:  Digitizers and AWGs by Spectrum now support ARM-based NVIDIA Jetson",
      "source": "https://www.einpresswire.com",
      "datetime": 1615973970,
      "publish_date": "2021-03-17 09:39:30",
      "original_url": "https://finnhub.io/api/news?id=0a10f3e06dc0b7eb34b98685e083853f43bb51f537ce863f207b447ae8a4577f",
      "final_url": "https://www.einpresswire.com/article/537043504/spectrum-pr-digitizers-and-awgs-by-spectrum-now-support-arm-based-nvidia-jetson",
      "is_yahoo_finance": false,
      "has_continue_reading": false,
      "url_check_status": "success",
      "url_check_error": null
    },
    {
      "headline": "Cryptocurrency Miners Gains Access RTX 3060 Desirable Hash Rates Due to Nivida Accidentally Unlocking Them",
      "source": "https://www.techtimes.com",
      "datetime": 1615917000,
      "publish_date": "2021-03-16 17:50:00",
      "original_url": "https://finnhub.io/api/news?id=2a0ae05b8c63d2a848bf24ce7dbfe24368d0a68a245c7c652b77a736ff6946d3",
      "final_url": "https://www.techtimes.com/articles/258075/20210316/nvidia-accidentally-unlocks-hash-rate-desirable-for-cryptocurrency-miners-for-rtx-3060-in-bid-to-discourage-them.htm",
      "is_yahoo_finance": false,
      "has_continue_reading": false,
      "url_check_status": "success",
      "url_check_error": null
    },
    {
      "headline": "Nvidia Admits Ethereum Mining Limitations Lifted Accidentally - BeInCrypto",
      "source": "https://beincrypto.com",
      "datetime": 1615913505,
      "publish_date": "2021-03-16 16:51:45",
      "original_url": "https://finnhub.io/api/news?id=e8c5e3f86982dd724fbbfe4543f8ab2f41023c256bef7ccad4c69c40066eb116",
      "final_url": "https://beincrypto.com/nvidia-admits-ethereum-mining-limitations-lifted-accidentally/",
      "is_yahoo_finance": false,
      "has_continue_reading": false,
      "url_check_status": "success",
      "url_check_error": null
    },
    {
      "headline": "Nvidia confirms it accidentally unlocked RTX 3060 Ethereum mining",
      "source": "https://www.theverge.com",
      "datetime": 1615891233,
      "publish_date": "2021-03-16 10:40:33",
      "original_url": "https://finnhub.io/api/news?id=97cbf29baabdc25cc4213559f3776c694ffd34f755d9e1ea9f3e64cf2bbe1ee8",
      "final_url": "https://www.theverge.com/2021/3/16/22333544/nvidia-rtx-3060-ethereum-mining-rate-limit-unlock-driver",
      "is_yahoo_finance": false,
      "has_continue_reading": false,
      "url_check_status": "success",
      "url_check_error": null
    },
    {
      "headline": "Choppy Trading Possible Over Next Two Days While Market Awaits Fed Verdict",
      "source": "Benzinga",
      "datetime": 1615887540,
      "publish_date": "2021-03-16 09:39:00",
      "original_url": "https://finnhub.io/api/news?id=a0cd596df85eca53fc206c8eee515cdd5064dab7a75c0ccc5449a0c19d4d9159",
      "final_url": "https://www.benzinga.com/news/earnings/21/03/20190374/choppy-trading-possible-over-next-two-days-while-market-awaits-fed-verdict",
      "is_yahoo_finance": false,
      "has_continue_reading": false,
      "url_check_status": "success",
      "url_check_error": null
    },
    {
      "headline": "ByteDance Moves Into Semiconductors, Goes On Hiring Spree: Bloomberg",
      "source": "benzinga",
      "datetime": 1615852800,
      "publish_date": "2021-03-16 00:00:00",
      "original_url": "https://finnhub.io/api/news?id=6c749d3d9c897475d99ebaba8533ba935b79307dc9c3add142a0d26fdf7143e3",
      "final_url": "https://www.benzinga.com/news/21/03/20183951/bytedance-moves-into-semiconductors-goes-on-hiring-spree-bloomberg",
      "is_yahoo_finance": false,
      "has_continue_reading": false,
      "url_check_status": "success",
      "url_check_error": null
    },
    {
      "headline": "Why Nvidia May Have Just Worsened GeForce RTX 3060 Availability",
      "source": "https://screenrant.com",
      "datetime": 1615837193,
      "publish_date": "2021-03-15 19:39:53",
      "original_url": "https://finnhub.io/api/news?id=2436b4354fe06d47a198e1bb0f21711b68b00ef55867d1e0a965f618e6133fe7",
      "final_url": "https://screenrant.com/nvidia-just-worsened-geforce-rtx-3060-availability/",
      "is_yahoo_finance": false,
      "has_continue_reading": false,
      "url_check_status": "success",
      "url_check_error": null
    },
    {
      "headline": "RTX 3060 cryptocurrency mining capabilities unlocked with beta NVIDIA driver",
      "source": "https://www.slashgear.com",
      "datetime": 1615827096,
      "publish_date": "2021-03-15 16:51:36",
      "original_url": "https://finnhub.io/api/news?id=69deed818e5d30bea14b94191378fd6afef0f6dee037d32443158fe9b7bee1f7",
      "final_url": "https://www.slashgear.com/rtx-3060-cryptocurrency-mining-capabilities-unlocked-with-beta-nvidia-driver-15663673/",
      "is_yahoo_finance": false,
      "has_continue_reading": false,
      "url_check_status": "success",
      "url_check_error": null
    },
    {
      "headline": "Latest RTX 3060 beta driver removes the limit on crypto mining",
      "source": "https://www.windowscentral.com",
      "datetime": 1615826047,
      "publish_date": "2021-03-15 16:34:07",
      "original_url": "https://finnhub.io/api/news?id=2771e85f7585cc156e27598c402220dce34b74f7c1d350f6675f8619518714e0",
      "final_url": "https://www.windowscentral.com/did-nvidia-just-give-slowing-rtx-3060-down-crypto-mining",
      "is_yahoo_finance": false,
      "has_continue_reading": false,
      "url_check_status": "success",
      "url_check_error": null
    },
    {
      "headline": "Nvidia’s new beta driver unlocks RTX 3060 Ethereum cryptocurrency mining",
      "source": "https://www.theverge.com",
      "datetime": 1615818157,
      "publish_date": "2021-03-15 14:22:37",
      "original_url": "https://finnhub.io/api/news?id=b39c1c0fce58392ef02f3a16ba6f37e692d23d224752fe4cd072c2a187f25bda",
      "final_url": "https://www.theverge.com/2021/3/15/22331537/nvidia-rtx-3060-ethereum-cryptocurrency-mining",
      "is_yahoo_finance": false,
      "has_continue_reading": false,
      "url_check_status": "success",
      "url_check_error": null
    },
    {
      "headline": "QCT utilise les nouveaux processeurs AMD EPYC™ 7003 pour accroître les performances et la valeur des centres de données modernes",
      "source": "businesswire",
      "datetime": 1615766400,
      "publish_date": "2021-03-15 00:00:00",
      "original_url": "https://finnhub.io/api/news?id=0e696926481c2038105b6f1f188769aefcee7790738db5d91b0ee1b4946e2b31",
      "final_url": "https://www.businesswire.com/news/home/20210315005830/fr",
      "is_yahoo_finance": false,
      "has_continue_reading": false,
      "url_check_status": "success",
      "url_check_error": null
    },
    {
      "headline": "Which GPU should you buy: NVIDIA GeForce RTX 3060 or RTX 3060 Ti?",
      "source": "https://www.windowscentral.com",
      "datetime": 1615730402,
      "publish_date": "2021-03-14 14:00:02",
      "original_url": "https://finnhub.io/api/news?id=56fca078e94e211080c78fdf5dbff1b3a740067d381bf0ac7689240fa76520fa",
      "final_url": "https://www.windowscentral.com/nvidia-geforce-rtx-3060-vs-rtx-3060-ti",
      "is_yahoo_finance": false,
      "has_continue_reading": false,
      "url_check_status": "success",
      "url_check_error": null
    },
    {
      "headline": "NVIDIA Continues Outpacing AMD in Graphics Cards, and It Isn't Done Yet | The Motley Fool",
      "source": "https://www.fool.com",
      "datetime": 1615722300,
      "publish_date": "2021-03-14 11:45:00",
      "original_url": "https://finnhub.io/api/news?id=498b2e69a2339edc188ef6334e7008f9a972a16b6db589b1e679590e825a50c9",
      "final_url": "https://www.fool.com/investing/2021/03/14/nvidia-continues-outpacing-amd-in-graphics-cards-a/",
      "is_yahoo_finance": false,
      "has_continue_reading": false,
      "url_check_status": "success",
      "url_check_error": null
    },
    {
      "headline": "3 Growth ETFs That Can Make You a Multimillionaire",
      "source": "Nasdaq",
      "datetime": 1615710600,
      "publish_date": "2021-03-14 08:30:00",
      "original_url": "https://finnhub.io/api/news?id=8c512958d234831ff47d3a3506328903a39a51fb6f5e53319c25d91d24d6f1e8",
      "final_url": "https://www.nasdaq.com/articles/3-growth-etfs-that-can-make-you-a-multimillionaire-2021-03-14",
      "is_yahoo_finance": false,
      "has_continue_reading": false,
      "url_check_status": "success",
      "url_check_error": null
    },
    {
      "headline": "Should you upgrade to the NVIDIA GeForce RTX 3060 from the RTX 2060 SUPER?",
      "source": "https://www.windowscentral.com",
      "datetime": 1615640402,
      "publish_date": "2021-03-13 13:00:02",
      "original_url": "https://finnhub.io/api/news?id=81a29514e14aadf9e6b0387706e6bc6c8bd0fd1a47c08e2888ee54dac9e1d5e1",
      "final_url": "https://www.windowscentral.com/nvidia-geforce-rtx-3060-vs-rtx-2060-super",
      "is_yahoo_finance": false,
      "has_continue_reading": false,
      "url_check_status": "success",
      "url_check_error": null
    },
    {
      "headline": "Which GPU should you buy: NVIDIA GeForce RTX 3060 Ti or RTX 3070?",
      "source": "https://www.windowscentral.com",
      "datetime": 1615561203,
      "publish_date": "2021-03-12 15:00:03",
      "original_url": "https://finnhub.io/api/news?id=8d88d01f83c893abfa1c842da2579969faa20f4cbe402bcfdf670ad328991d8f",
      "final_url": "https://www.windowscentral.com/nvidia-geforce-rtx-3060-ti-vs-rtx-3070",
      "is_yahoo_finance": false,
      "has_continue_reading": false,
      "url_check_status": "success",
      "url_check_error": null
    },
    {
      "headline": "Nvidia GeForce RTX 3060 review: It's fine",
      "source": "https://www.pcworld.com",
      "datetime": 1615507200,
      "publish_date": "2021-03-12 00:00:00",
      "original_url": "https://finnhub.io/api/news?id=ac3b750370ebe661a2c1ad409242cf1ea151fa96b504c8c2164ded66297924ad",
      "final_url": "https://www.pcworld.com/article/394228/nvidia-geforce-rtx-3060-review.html",
      "is_yahoo_finance": false,
      "has_continue_reading": false,
      "url_check_status": "success",
      "url_check_error": null
    },
    {
      "headline": "Nvidia Says It's Achieved ‘Near-Bare-Metal’ AI Performance on vSphere",
      "source": "https://www.datacenterknowledge.com",
      "datetime": 1615490837,
      "publish_date": "2021-03-11 19:27:17",
      "original_url": "https://finnhub.io/api/news?id=fea6dafffba99b90c046abebd1e6fddf181fd672b2c1ae207e87a45673228f77",
      "final_url": "https://www.datacenterknowledge.com/servers/nvidia-says-it-s-achieved-near-bare-metal-ai-performance-on-vsphere",
      "is_yahoo_finance": false,
      "has_continue_reading": false,
      "url_check_status": "success",
      "url_check_error": null
    },
    {
      "headline": "Should you upgrade to the NVIDIA GeForce RTX 3060 from the RTX 2060?",
      "source": "https://www.windowscentral.com",
      "datetime": 1615474802,
      "publish_date": "2021-03-11 15:00:02",
      "original_url": "https://finnhub.io/api/news?id=389a17d5c43f1b31d2f9f56b0164fa35886a7cd3a1d0444d8d27d5fd6b272d09",
      "final_url": "https://www.windowscentral.com/nvidia-geforce-rtx-3060-vs-rtx-2060",
      "is_yahoo_finance": false,
      "has_continue_reading": false,
      "url_check_status": "success",
      "url_check_error": null
    },
    {
      "headline": "Nvidia Stock Slides Further, Offering a Buying Opportunity",
      "source": "https://investorplace.com",
      "datetime": 1615401396,
      "publish_date": "2021-03-10 18:36:36",
      "original_url": "https://finnhub.io/api/news?id=c8b9493cce0e41a79e6eedd46e2dbbfd6a4f9aa52c636b3bc2318f320bf7cf91",
      "final_url": "https://investorplace.com/2021/03/nvda-stock-slides-further-offers-a-buying-opportunity/",
      "is_yahoo_finance": false,
      "has_continue_reading": false,
      "url_check_status": "success",
      "url_check_error": null
    },
    {
      "headline": "Get your PC ready for an NVIDIA RTX 3060 upgrade with one of these PSUs",
      "source": "https://www.windowscentral.com",
      "datetime": 1615383002,
      "publish_date": "2021-03-10 13:30:02",
      "original_url": "https://finnhub.io/api/news?id=98e68e24bd88cf7beba869f522ab7f33298b9ffc524a7222a5af763541d41792",
      "final_url": "https://www.windowscentral.com/best-psu-nvidia-rtx-3060",
      "is_yahoo_finance": false,
      "has_continue_reading": false,
      "url_check_status": "success",
      "url_check_error": null
    },
    {
      "headline": "The AI-Ready Enterprise Platform: Unleashing AI for Every Enterprise",
      "source": "https://blogs.vmware.com",
      "datetime": 1615323717,
      "publish_date": "2021-03-09 21:01:57",
      "original_url": "https://finnhub.io/api/news?id=d60bba2bf3167051b8914dc7d342ddca4abae305d6a2360cc8e930191e68fd4c",
      "final_url": "https://blogs.vmware.com/vsphere/2021/03/ai-ready-enterprise-platform-unleashing-ai-every-enterprise.html",
      "is_yahoo_finance": false,
      "has_continue_reading": false,
      "url_check_status": "success",
      "url_check_error": null
    },
    {
      "headline": "Announcing: vSphere 7 Update 2 Release - VMware vSphere Blog",
      "source": "https://blogs.vmware.com",
      "datetime": 1615323630,
      "publish_date": "2021-03-09 21:00:30",
      "original_url": "https://finnhub.io/api/news?id=49086fdf6e2abc1857be6671331dec8b9248438a8de0a9cf1d5441e76f758f0c",
      "final_url": "https://blogs.vmware.com/vsphere/2021/03/announcing-vsphere-7-update-2-release.html",
      "is_yahoo_finance": false,
      "has_continue_reading": false,
      "url_check_status": "success",
      "url_check_error": null
    },
    {
      "headline": "Stocks making the biggest moves midday: Tesla, Stitch Fix, Dick's Sporting Goods & more",
      "source": "CNBC",
      "datetime": 1615310206,
      "publish_date": "2021-03-09 17:16:46",
      "original_url": "https://finnhub.io/api/news?id=0399b61aa72619771f40fae41553e310caeb51996d1c3ec629f88f7e4b0a5f58",
      "final_url": "https://www.cnbc.com/2021/03/09/stocks-making-the-biggest-moves-midday-tesla-stitch-fix-dicks-sporting-goods-more.html",
      "is_yahoo_finance": false,
      "has_continue_reading": false,
      "url_check_status": "success",
      "url_check_error": null
    },
    {
      "headline": "NVIDIA Unveils AI Enterprise Software Suite To Unleash The Power Of AI",
      "source": "https://analyticsindiamag.com",
      "datetime": 1615300223,
      "publish_date": "2021-03-09 14:30:23",
      "original_url": "https://finnhub.io/api/news?id=9ddd27675f54cebe22816daa38747e65744e2f98a05b3e072793b1622d362b2d",
      "final_url": "https://analyticsindiamag.com/ai-news-updates/nvidia-unveils-ai-enterprise-software-suite-to-unleash-the-power-of-ai/",
      "is_yahoo_finance": false,
      "has_continue_reading": false,
      "url_check_status": "success",
      "url_check_error": null
    },
    {
      "headline": "This Cloud Computing Subsector Has Huge Potential: 2 Stocks to Buy Before the Boom | The Motley Fool",
      "source": "https://www.fool.com",
      "datetime": 1615299546,
      "publish_date": "2021-03-09 14:19:06",
      "original_url": "https://finnhub.io/api/news?id=419cc4aabe192dde98071a43c867361133ed97023fb6a7b00ebec1d0eb5832c2",
      "final_url": "https://www.fool.com/investing/2021/03/09/this-cloud-computing-subsector-has-huge-potential/",
      "is_yahoo_finance": false,
      "has_continue_reading": false,
      "url_check_status": "success",
      "url_check_error": null
    },
    {
      "headline": "NVIDIA CEO Jensen Huang to Host AI Pioneers Yoshua Bengio, Geoffrey Hinton and Yann LeCun, and Others, at GTC21",
      "source": "https://www.einpresswire.com",
      "datetime": 1615298400,
      "publish_date": "2021-03-09 14:00:00",
      "original_url": "https://finnhub.io/api/news?id=b16b29c581fd4f75769b045e4a68f18457f4ec3c6737a3e85c67c155fe10d7f2",
      "final_url": "https://www.einpresswire.com/article/536582765/nvidia-ceo-jensen-huang-to-host-ai-pioneers-yoshua-bengio-geoffrey-hinton-and-yann-lecun-and-others-at-gtc21",
      "is_yahoo_finance": false,
      "has_continue_reading": false,
      "url_check_status": "success",
      "url_check_error": null
    },
    {
      "headline": "This Vanguard Fund Is the Bitcoin of ETFs",
      "source": "Nasdaq",
      "datetime": 1615278600,
      "publish_date": "2021-03-09 08:30:00",
      "original_url": "https://finnhub.io/api/news?id=3c4740f59d38627da92d5828650ab2fbae24708440b9ec0d2fd51622fc34f82e",
      "final_url": "https://www.nasdaq.com/articles/this-vanguard-fund-is-the-bitcoin-of-etfs-2021-03-09",
      "is_yahoo_finance": false,
      "has_continue_reading": false,
      "url_check_status": "success",
      "url_check_error": null
    },
    {
      "headline": "Is the RTX 3080 or the RX 6800 a better GPU for your next PC build?",
      "source": "https://www.windowscentral.com",
      "datetime": 1615240803,
      "publish_date": "2021-03-08 22:00:03",
      "original_url": "https://finnhub.io/api/news?id=b08d28612cc4c4fdd5bf2221294112738d77c414477a8d93f4e7b5b2d217a0ea",
      "final_url": "https://www.windowscentral.com/rtx-3080-vs-rx-6800",
      "is_yahoo_finance": false,
      "has_continue_reading": false,
      "url_check_status": "success",
      "url_check_error": null
    },
    {
      "headline": "NVIDIA A100, A40 and NVIDIA RTX A6000 Ampere Architecture-Based Professional GPUs Transform Data Science and Big Data Analytics - insideBIGDATA",
      "source": "https://insidebigdata.com",
      "datetime": 1615212000,
      "publish_date": "2021-03-08 14:00:00",
      "original_url": "https://finnhub.io/api/news?id=1fcac8c944a1bf7bece38abe2583f103d915e67567bdf84925c75c4965e197f0",
      "final_url": "http://insideainews.com/2021/03/08/nvidia-a100-a40-and-nvidia-rtx-a6000-ampere-architecture-based-professional-gpus-transform-data-science-and-big-data-analytics/",
      "is_yahoo_finance": false,
      "has_continue_reading": false,
      "url_check_status": "success",
      "url_check_error": null
    },
    {
      "headline": "4 Stocks Hampered by This Continued Shortage of Semiconductors",
      "source": "https://investorplace.com",
      "datetime": 1615208607,
      "publish_date": "2021-03-08 13:03:27",
      "original_url": "https://finnhub.io/api/news?id=35e0cf45d63153b25716e817d582c96d40b3ea410aab7bd92a9e5ea299b8ea86",
      "final_url": "https://investorplace.com/2021/03/4-stocks-hampered-by-this-continued-shortage-of-semiconductors/",
      "is_yahoo_finance": false,
      "has_continue_reading": false,
      "url_check_status": "success",
      "url_check_error": null
    },
    {
      "headline": "Les ventes de GPU ont explos",
      "source": "https://www.lemondeinformatique.fr",
      "datetime": 1615207515,
      "publish_date": "2021-03-08 12:45:15",
      "original_url": "https://finnhub.io/api/news?id=69a118e998b2032e33639378cf24e022525a441564aef8d61f6cd057b0718e47",
      "final_url": "https://www.lemondeinformatique.fr/actualites/lire-les-ventes-de-gpu-ont-explose-fin-2020-selon-jpr-82205.html",
      "is_yahoo_finance": false,
      "has_continue_reading": false,
      "url_check_status": "success",
      "url_check_error": null
    },
    {
      "headline": "Get Paid While You Wait: 3 Top Dividend Stocks in the Technology Sector",
      "source": "Nasdaq",
      "datetime": 1615193700,
      "publish_date": "2021-03-08 08:55:00",
      "original_url": "https://finnhub.io/api/news?id=ee313a903155426dcc09d8b3fc5473fa113ab27aae74649b7f2b34ad3691c360",
      "final_url": "https://www.nasdaq.com/articles/get-paid-while-you-wait%3A-3-top-dividend-stocks-in-the-technology-sector-2021-03-08",
      "is_yahoo_finance": false,
      "has_continue_reading": false,
      "url_check_status": "success",
      "url_check_error": null
    },
    {
      "headline": "This ETF Could Help Grow Your Retirement Account",
      "source": "Nasdaq",
      "datetime": 1615183560,
      "publish_date": "2021-03-08 06:06:00",
      "original_url": "https://finnhub.io/api/news?id=97ffc8f13b143003c02da292d4361bcd7c0eb7d57d35d4fccbdc3e6d45a42901",
      "final_url": "https://www.nasdaq.com/articles/this-etf-could-help-grow-your-retirement-account-2021-03-08",
      "is_yahoo_finance": false,
      "has_continue_reading": false,
      "url_check_status": "success",
      "url_check_error": null
    },
    {
      "headline": "How Nintendo and Nvidia could bring 4K to the Super Nintendo Switch",
      "source": "https://venturebeat.com",
      "datetime": 1615126592,
      "publish_date": "2021-03-07 14:16:32",
      "original_url": "https://finnhub.io/api/news?id=9338f8e919b2d247857a9956a07ceb69462a9856446c16b252e52a81810d0bad",
      "final_url": "https://venturebeat.com/games/how-nintendo-and-nvidia-could-bring-4k-to-the-super-nintendo-switch/",
      "is_yahoo_finance": false,
      "has_continue_reading": false,
      "url_check_status": "success",
      "url_check_error": null
    },
    {
      "headline": "Unannounced Nvidia RTX 3050 Ti GPU appears on Asus’ website",
      "source": "https://www.theverge.com",
      "datetime": 1614954629,
      "publish_date": "2021-03-05 14:30:29",
      "original_url": "https://finnhub.io/api/news?id=b48544d760afe35ca5bb7aa4f2bf476efb6885fe4a2aa3f5e92e6666983b0681",
      "final_url": "https://www.theverge.com/2021/3/5/22315175/nvidia-rtx-3050-ti-gpu-asus-leak-rumor",
      "is_yahoo_finance": false,
      "has_continue_reading": false,
      "url_check_status": "success",
      "url_check_error": null
    },
    {
      "headline": "AMD RX 6700 XT vs. Nvidia RTX 3070 | Digital Trends",
      "source": "https://www.digitaltrends.com",
      "datetime": 1614942021,
      "publish_date": "2021-03-05 11:00:21",
      "original_url": "https://finnhub.io/api/news?id=a8b3936260d500722c5891b9860a0babadd43a4f108f084251de1001c46e94fe",
      "final_url": "https://www.digitaltrends.com/computing/rx-6700-xt-vs-rtx-3070/",
      "is_yahoo_finance": false,
      "has_continue_reading": false,
      "url_check_status": "success",
      "url_check_error": null
    },
    {
      "headline": "Ex-Dividend Reminder: NVIDIA, Rogers Communications and Bentley Systems",
      "source": "Nasdaq",
      "datetime": 1614941772,
      "publish_date": "2021-03-05 10:56:12",
      "original_url": "https://finnhub.io/api/news?id=a36fa03e5d80debecba9dfd43735182d43812f7ee23273aa62a87cc13d816c4d",
      "final_url": "https://www.nasdaq.com/articles/ex-dividend-reminder%3A-nvidia-rogers-communications-and-bentley-systems-2021-03-05",
      "is_yahoo_finance": false,
      "has_continue_reading": false,
      "url_check_status": "success",
      "url_check_error": null
    },
    {
      "headline": "iPad 2020 Rumors to Feature 10.9-inch OLED Displays",
      "source": "https://www.techtimes.com",
      "datetime": 1614930709,
      "publish_date": "2021-03-05 07:51:49",
      "original_url": "https://finnhub.io/api/news?id=45a4cd84f773b908229a231ce02c2c10dbe38626e0aa9bd726f8eb2303f0ca4a",
      "final_url": "https://www.techtimes.com/articles/257705/20210305/macbook-ipad-2022-rumors-oled-displays-sizes-10-9-inch.htm",
      "is_yahoo_finance": false,
      "has_continue_reading": false,
      "url_check_status": "success",
      "url_check_error": null
    },
    {
      "headline": "3 Reasons NVIDIA's Gaming Growth Is Legit | The Motley Fool",
      "source": "https://www.fool.com",
      "datetime": 1614878159,
      "publish_date": "2021-03-04 17:15:59",
      "original_url": "https://finnhub.io/api/news?id=b6b0af01032c1c753e3602dd29677c7715cd359ad5357d50999ae976982e2ea9",
      "final_url": "https://www.fool.com/investing/2021/03/04/3-reasons-nvidias-gaming-growth-is-legit/",
      "is_yahoo_finance": false,
      "has_continue_reading": false,
      "url_check_status": "success",
      "url_check_error": null
    },
    {
      "headline": "Noteworthy ETF Outflows: IWF, NVDA, AVGO, HD",
      "source": "Nasdaq",
      "datetime": 1614855300,
      "publish_date": "2021-03-04 10:55:00",
      "original_url": "https://finnhub.io/api/news?id=54f1ebe9c76ebcd3cd76808189b0ac6220cc50bba8da75c4c6a19e4c67793c94",
      "final_url": "https://www.nasdaq.com/articles/noteworthy-etf-outflows%3A-iwf-nvda-avgo-hd-2021-03-04",
      "is_yahoo_finance": false,
      "has_continue_reading": false,
      "url_check_status": "success",
      "url_check_error": null
    },
    {
      "headline": "More Pressure On Tech Sector To Start Day, With Apple, Microsoft Both Lower",
      "source": "Benzinga",
      "datetime": 1614850860,
      "publish_date": "2021-03-04 09:41:00",
      "original_url": "https://finnhub.io/api/news?id=036c85d4d84588a8343a30d63cc534299bb4c48ec9dda508f2af8eca3f078fb2",
      "final_url": "https://www.benzinga.com/news/earnings/21/03/20009083/more-pressure-on-tech-sector-to-start-day-with-apple-microsoft-both-lower",
      "is_yahoo_finance": false,
      "has_continue_reading": false,
      "url_check_status": "success",
      "url_check_error": null
    },
    {
      "headline": "AMD Radeon RX 6700 XT detailed with March release date",
      "source": "https://www.slashgear.com",
      "datetime": 1614788847,
      "publish_date": "2021-03-03 16:27:27",
      "original_url": "https://finnhub.io/api/news?id=1c5f7140b084773c6baa47f146f2a68bcba4828046a07ad382c25cd5cb69af18",
      "final_url": "https://www.slashgear.com/amd-radeon-rx-6700-xt-detailed-with-march-release-date-03662128/",
      "is_yahoo_finance": false,
      "has_continue_reading": false,
      "url_check_status": "success",
      "url_check_error": null
    },
    {
      "headline": "AMD will announce its next RX 6000-series GPU today; here's how to watch",
      "source": "https://www.windowscentral.com",
      "datetime": 1614786301,
      "publish_date": "2021-03-03 15:45:01",
      "original_url": "https://finnhub.io/api/news?id=68df7c2f9fdfb9c3fe17fa8bee74a16c1b9e8fb8bb934aa9f72881ba87bbf84e",
      "final_url": "https://www.windowscentral.com/how-watch-amd-announce-next-radeon-rx-6000-gpu",
      "is_yahoo_finance": false,
      "has_continue_reading": false,
      "url_check_status": "success",
      "url_check_error": null
    },
    {
      "headline": "Velodyne Lidar Anuncia Cúpula Virtual Gratuita, Mulheres Disruptivas Impulsionando Nosso Futuro Autônomo",
      "source": "businesswire",
      "datetime": 1614729600,
      "publish_date": "2021-03-03 00:00:00",
      "original_url": "https://finnhub.io/api/news?id=c292332933a4510b983010d7b6547aeade5930b3448445691ce837698af54100",
      "final_url": "https://www.businesswire.com/news/home/20210303005713/pt",
      "is_yahoo_finance": false,
      "has_continue_reading": false,
      "url_check_status": "success",
      "url_check_error": null
    },
    {
      "headline": "Can You Mine Ethereum With PlayStation 5? Here's What You Should Know",
      "source": "benzinga",
      "datetime": 1614643200,
      "publish_date": "2021-03-02 00:00:00",
      "original_url": "https://finnhub.io/api/news?id=228feb6d4544943e07eab33acae16d5c479f799ff66cb65420e38e49b91b0d96",
      "final_url": "https://www.benzinga.com/markets/cryptocurrency/21/03/19931036/can-you-mine-ethereum-with-playstation-5-heres-what-you-should-know",
      "is_yahoo_finance": false,
      "has_continue_reading": false,
      "url_check_status": "success",
      "url_check_error": null
    },
    {
      "headline": "Global 3D Glasses Market Report 2020: Market to Reach $13.1 Billion by 2027 - Anaglyph 3D Glasses is Projected to Account for $1.3 Billion - ResearchAndMarkets.com",
      "source": "businesswire",
      "datetime": 1614643200,
      "publish_date": "2021-03-02 00:00:00",
      "original_url": "https://finnhub.io/api/news?id=d38f169e0312cca785d7ce5e040941caf0fd10eee8df16c91bc6f2599679b85e",
      "final_url": "https://www.businesswire.com/news/home/20210302005536/en/Global-3D-Glasses-Market-Report-2020-Market-to-Reach-%2413.1-Billion-by-2027---Anaglyph-3D-Glasses-is-Projected-to-Account-for-%241.3-Billion---ResearchAndMarkets.com",
      "is_yahoo_finance": false,
      "has_continue_reading": false,
      "url_check_status": "success",
      "url_check_error": null
    },
    {
      "headline": "Notable Monday Option Activity: NFLX, NVDA, JNJ",
      "source": "Nasdaq",
      "datetime": 1614606276,
      "publish_date": "2021-03-01 13:44:36",
      "original_url": "https://finnhub.io/api/news?id=f25e7cc8f3fb512fd41bdac0af5c305fa71a36e7e67a7a979845644dfde431d0",
      "final_url": "https://www.nasdaq.com/articles/notable-monday-option-activity%3A-nflx-nvda-jnj-2021-03-01",
      "is_yahoo_finance": false,
      "has_continue_reading": false,
      "url_check_status": "success",
      "url_check_error": null
    },
    {
      "headline": "Nvidia resists UK jobs guarantee after $40bn Arm takeover - CityAM",
      "source": "https://www.cityam.com",
      "datetime": 1614604019,
      "publish_date": "2021-03-01 13:06:59",
      "original_url": "https://finnhub.io/api/news?id=806476c8548c8f63a8e2b4ea17c9eac297c2fbb892d5e0afd4abd262da4fd481",
      "final_url": "https://www.cityam.com/nvidia-resists-uk-jobs-guarantee-after-40bn-arm-takeover/",
      "is_yahoo_finance": false,
      "has_continue_reading": false,
      "url_check_status": "success",
      "url_check_error": null
    },
    {
      "headline": "'There is no alternative' — stocks' long-running 'TINA' advantage could be ending, worrying traders",
      "source": "CNBC",
      "datetime": 1614600184,
      "publish_date": "2021-03-01 12:03:04",
      "original_url": "https://finnhub.io/api/news?id=aeb3d17c0ca592e6c19354faf71f4dd8e6b74f084fbcac5fd748c47293170f9c",
      "final_url": "https://www.cnbc.com/2021/03/01/there-is-no-alternative-stocks-long-running-tina-advantage-could-be-ending-worrying-traders.html",
      "is_yahoo_finance": false,
      "has_continue_reading": false,
      "url_check_status": "success",
      "url_check_error": null
    },
    {
      "headline": "You only need a screen: Nvidia GeForce Now arrives in Turkey",
      "source": "https://www.dailysabah.com",
      "datetime": 1614597420,
      "publish_date": "2021-03-01 11:17:00",
      "original_url": "https://finnhub.io/api/news?id=737f4b857bfc59bb0cd532748ebd88a5d92c15c5228e956740046d707929ce9e",
      "final_url": "https://www.dailysabah.com/life/you-only-need-a-screen-nvidia-geforce-now-arrives-in-turkey/news",
      "is_yahoo_finance": false,
      "has_continue_reading": false,
      "url_check_status": "success",
      "url_check_error": null
    },
    {
      "headline": "Analysts See 10% Gains Ahead For The Holdings of SPHQ",
      "source": "Nasdaq",
      "datetime": 1614594497,
      "publish_date": "2021-03-01 10:28:17",
      "original_url": "https://finnhub.io/api/news?id=616235b6744c0ec866e5c48a61b7730e2b31a8982142188d2030c3593faacc4f",
      "final_url": "https://www.nasdaq.com/articles/analysts-see-10-gains-ahead-for-the-holdings-of-sphq-2021-03-01",
      "is_yahoo_finance": false,
      "has_continue_reading": false,
      "url_check_status": "success",
      "url_check_error": null
    },
    {
      "headline": "Where to Buy a RTX 3060 Ti Graphics Card?: Nvidia Video Card Depleting in Storage for Cheaper Price",
      "source": "https://www.techtimes.com",
      "datetime": 1614564480,
      "publish_date": "2021-03-01 02:08:00",
      "original_url": "https://finnhub.io/api/news?id=da088691d65704978fb74d7c4801fcd411f91ac781de61c870651a9ccc6f880e",
      "final_url": "https://www.techtimes.com/articles/257513/20210228/where-purchase-rtx-3060-ti-3070-3080-30xx-line-up.htm",
      "is_yahoo_finance": false,
      "has_continue_reading": false,
      "url_check_status": "success",
      "url_check_error": null
    }
  ]
}